{
  "configurations": [
    {
      "name": "WSL-GCC-Debug",
      "generator": "Ninja",
      "configurationType": "Debug",
      "buildRoot": "${projectDir}\\out\\build\\${name}",
      "installRoot": "${projectDir}\\out\\install\\${name}",
      "cmakeExecutable": "cmake",
      "cmakeCommandArgs": "-DSETUP_MODE:BOOL=OFF -DROOT=/mnt/d/Projects/6.Projects/tebako/tests/test-01 -DENTRANCE=test.rb -DPCKG=test-01-package",
      "buildCommandArgs": "",
      "ctestCommandArgs": "",
      "inheritEnvironments": [ "linux_x64" ],
      "wslPath": "C:\\Users\\Maxim\\AppData\\Local\\Microsoft\\WindowsApps\\ubuntu2004.exe"
    }
  ]
}